dkov_py_testpackage_001/utils.py
dkov_py_testpackage_001-0.0.7.dist-info/licenses/LICENSE
dkov_py_testpackage_001-0.0.7.dist-info/METADATA
dkov_py_testpackage_001-0.0.7.dist-info/WHEEL
dkov_py_testpackage_001-0.0.7.dist-info/top_level.txt
dkov_py_testpackage_001-0.0.7.dist-info/RECORD
