Metadata-Version: 2.4
Name: dkov.py.testpackage_001
Version: 0.0.7
Summary: Test Package
Author-email: Dmitry Kovalenko <dmitry.lipetsk@gmail.com>
License: WTFPL
Project-URL: HomePage, https://github.com/dmitry-lipetsk/dkov.py.testpackage_001
Keywords: test,testing,postgresql
Classifier: Programming Language :: Python :: 3 :: Only
Classifier: Programming Language :: Python :: 3.7
Classifier: Programming Language :: Python :: 3.8
Classifier: Programming Language :: Python :: 3.9
Classifier: Programming Language :: Python :: 3.10
Classifier: Programming Language :: Python :: 3.11
Classifier: Programming Language :: Python :: 3.12
Classifier: Programming Language :: Python :: 3.13
Classifier: Programming Language :: Python :: 3.14
Requires-Python: >=3.7.17
License-File: LICENSE
Dynamic: license-file
